{
  "provider": "google_weather",
  "timestamp": "2026-01-26T05:35:49.336405",
  "api_success": true,
  "data": {
    "hourly": [
      {
        "time": "2026-01-26T08:00:00Z",
        "temp_c": 6.3,
        "feels_like_c": 6.3,
        "precip_prob": 10,
        "precip_mm": 0.0,
        "dewpoint_c": 4.7,
        "cloud_cover": 80,
        "wind_speed_kmh": 3.0,
        "condition": "Mostly cloudy",
        "is_daytime": false
      },
      {
        "time": "2026-01-26T09:00:00Z",
        "temp_c": 5.9,
        "feels_like_c": 5.9,
        "precip_prob": 10,
        "precip_mm": 0.0,
        "dewpoint_c": 4.4,
        "cloud_cover": 93,
        "wind_speed_kmh": 3.0,
        "condition": "Cloudy",
        "is_daytime": false
      },
      {
        "time": "2026-01-26T10:00:00Z",
        "temp_c": 5.7,
        "feels_like_c": 5.7,
        "precip_prob": 10,
        "precip_mm": 0.0,
        "dewpoint_c": 4.4,
        "cloud_cover": 95,
        "wind_speed_kmh": 2.0,
        "condition": "Cloudy",
        "is_daytime": false
      },
      {
        "time": "2026-01-26T11:00:00Z",
        "temp_c": 5.6,
        "feels_like_c": 5.6,
        "precip_prob": 10,
        "precip_mm": 0.0,
        "dewpoint_c": 4.3,
        "cloud_cover": 95,
        "wind_speed_kmh": 2.0,
        "condition": "Cloudy",
        "is_daytime": false
      },
      {
        "time": "2026-01-26T12:00:00Z",
        "temp_c": 5.4,
        "feels_like_c": 5.4,
        "precip_prob": 10,
        "precip_mm": 0.0,
        "dewpoint_c": 4.2,
        "cloud_cover": 95,
        "wind_speed_kmh": 0.0,
        "condition": "Cloudy",
        "is_daytime": false
      },
      {
        "time": "2026-01-26T13:00:00Z",
        "temp_c": 5.1,
        "feels_like_c": 5.1,
        "precip_prob": 10,
        "precip_mm": 0.0,
        "dewpoint_c": 3.7,
        "cloud_cover": 100,
        "wind_speed_kmh": 3.0,
        "condition": "Cloudy",
        "is_daytime": false
      },
      {
        "time": "2026-01-26T14:00:00Z",
        "temp_c": 4.7,
        "feels_like_c": 4.7,
        "precip_prob": 10,
        "precip_mm": 0.0,
        "dewpoint_c": 3.7,
        "cloud_cover": 100,
        "wind_speed_kmh": 3.0,
        "condition": "Cloudy",
        "is_daytime": false
      },
      {
        "time": "2026-01-26T15:00:00Z",
        "temp_c": 4.7,
        "feels_like_c": 4.7,
        "precip_prob": 10,
        "precip_mm": 0.0,
        "dewpoint_c": 3.9,
        "cloud_cover": 100,
        "wind_speed_kmh": 2.0,
        "condition": "Cloudy",
        "is_daytime": false
      },
      {
        "time": "2026-01-26T16:00:00Z",
        "temp_c": 4.9,
        "feels_like_c": 4.9,
        "precip_prob": 10,
        "precip_mm": 0.0,
        "dewpoint_c": 4.2,
        "cloud_cover": 100,
        "wind_speed_kmh": 3.0,
        "condition": "Cloudy",
        "is_daytime": true
      },
      {
        "time": "2026-01-26T17:00:00Z",
        "temp_c": 5.8,
        "feels_like_c": 5.0,
        "precip_prob": 10,
        "precip_mm": 0.0,
        "dewpoint_c": 4.8,
        "cloud_cover": 96,
        "wind_speed_kmh": 5.0,
        "condition": "Cloudy",
        "is_daytime": true
      },
      {
        "time": "2026-01-26T18:00:00Z",
        "temp_c": 6.7,
        "feels_like_c": 6.0,
        "precip_prob": 10,
        "precip_mm": 0.0,
        "dewpoint_c": 5.2,
        "cloud_cover": 95,
        "wind_speed_kmh": 5.0,
        "condition": "Cloudy",
        "is_daytime": true
      },
      {
        "time": "2026-01-26T19:00:00Z",
        "temp_c": 7.9,
        "feels_like_c": 7.0,
        "precip_prob": 10,
        "precip_mm": 0.0,
        "dewpoint_c": 5.6,
        "cloud_cover": 81,
        "wind_speed_kmh": 6.0,
        "condition": "Mostly cloudy",
        "is_daytime": true
      },
      {
        "time": "2026-01-26T20:00:00Z",
        "temp_c": 8.4,
        "feels_like_c": 8.0,
        "precip_prob": 5,
        "precip_mm": 0.0,
        "dewpoint_c": 6.1,
        "cloud_cover": 44,
        "wind_speed_kmh": 6.0,
        "condition": "Partly sunny",
        "is_daytime": true
      },
      {
        "time": "2026-01-26T21:00:00Z",
        "temp_c": 9.6,
        "feels_like_c": 9.0,
        "precip_prob": 0,
        "precip_mm": 0.0,
        "dewpoint_c": 6.3,
        "cloud_cover": 36,
        "wind_speed_kmh": 5.0,
        "condition": "Partly sunny",
        "is_daytime": true
      },
      {
        "time": "2026-01-26T22:00:00Z",
        "temp_c": 10.6,
        "feels_like_c": 10.6,
        "precip_prob": 0,
        "precip_mm": 0.0,
        "dewpoint_c": 6.4,
        "cloud_cover": 25,
        "wind_speed_kmh": 3.0,
        "condition": "Mostly sunny",
        "is_daytime": true
      },
      {
        "time": "2026-01-26T23:00:00Z",
        "temp_c": 11.9,
        "feels_like_c": 11.9,
        "precip_prob": 0,
        "precip_mm": 0.0,
        "dewpoint_c": 6.4,
        "cloud_cover": 31,
        "wind_speed_kmh": 2.0,
        "condition": "Partly sunny",
        "is_daytime": true
      },
      {
        "time": "2026-01-27T00:00:00Z",
        "temp_c": 12.6,
        "feels_like_c": 12.6,
        "precip_prob": 0,
        "precip_mm": 0.0,
        "dewpoint_c": 6.5,
        "cloud_cover": 40,
        "wind_speed_kmh": 2.0,
        "condition": "Partly sunny",
        "is_daytime": true
      },
      {
        "time": "2026-01-27T01:00:00Z",
        "temp_c": 11.9,
        "feels_like_c": 11.9,
        "precip_prob": 0,
        "precip_mm": 0.0,
        "dewpoint_c": 6.8,
        "cloud_cover": 20,
        "wind_speed_kmh": 2.0,
        "condition": "Mostly sunny",
        "is_daytime": true
      },
      {
        "time": "2026-01-27T02:00:00Z",
        "temp_c": 10.1,
        "feels_like_c": 10.1,
        "precip_prob": 0,
        "precip_mm": 0.0,
        "dewpoint_c": 6.4,
        "cloud_cover": 35,
        "wind_speed_kmh": 2.0,
        "condition": "Partly cloudy",
        "is_daytime": false
      },
      {
        "time": "2026-01-27T03:00:00Z",
        "temp_c": 9.1,
        "feels_like_c": 9.1,
        "precip_prob": 5,
        "precip_mm": 0.0,
        "dewpoint_c": 6.3,
        "cloud_cover": 60,
        "wind_speed_kmh": 3.0,
        "condition": "Partly cloudy",
        "is_daytime": false
      },
      {
        "time": "2026-01-27T04:00:00Z",
        "temp_c": 7.6,
        "feels_like_c": 7.6,
        "precip_prob": 10,
        "precip_mm": 0.0,
        "dewpoint_c": 5.6,
        "cloud_cover": 85,
        "wind_speed_kmh": 0.0,
        "condition": "Mostly cloudy",
        "is_daytime": false
      },
      {
        "time": "2026-01-27T05:00:00Z",
        "temp_c": 6.6,
        "feels_like_c": 6.6,
        "precip_prob": 10,
        "precip_mm": 0.0,
        "dewpoint_c": 5.1,
        "cloud_cover": 90,
        "wind_speed_kmh": 0.0,
        "condition": "Cloudy",
        "is_daytime": false
      },
      {
        "time": "2026-01-27T06:00:00Z",
        "temp_c": 5.9,
        "feels_like_c": 5.9,
        "precip_prob": 10,
        "precip_mm": 0.0,
        "dewpoint_c": 4.3,
        "cloud_cover": 93,
        "wind_speed_kmh": 2.0,
        "condition": "Cloudy",
        "is_daytime": false
      },
      {
        "time": "2026-01-27T07:00:00Z",
        "temp_c": 4.9,
        "feels_like_c": 4.9,
        "precip_prob": 10,
        "precip_mm": 0.0,
        "dewpoint_c": 3.8,
        "cloud_cover": 100,
        "wind_speed_kmh": 3.0,
        "condition": "Cloudy",
        "is_daytime": false
      },
      {
        "time": "2026-01-27T08:00:00Z",
        "temp_c": 4.8,
        "feels_like_c": 4.8,
        "precip_prob": 10,
        "precip_mm": 0.0,
        "dewpoint_c": 3.7,
        "cloud_cover": 100,
        "wind_speed_kmh": 3.0,
        "condition": "Cloudy",
        "is_daytime": false
      },
      {
        "time": "2026-01-27T09:00:00Z",
        "temp_c": 4.6,
        "feels_like_c": 4.6,
        "precip_prob": 10,
        "precip_mm": 0.0,
        "dewpoint_c": 3.5,
        "cloud_cover": 100,
        "wind_speed_kmh": 3.0,
        "condition": "Cloudy",
        "is_daytime": false
      },
      {
        "time": "2026-01-27T10:00:00Z",
        "temp_c": 4.4,
        "feels_like_c": 4.4,
        "precip_prob": 10,
        "precip_mm": 0.0,
        "dewpoint_c": 3.4,
        "cloud_cover": 100,
        "wind_speed_kmh": 3.0,
        "condition": "Cloudy",
        "is_daytime": false
      },
      {
        "time": "2026-01-27T11:00:00Z",
        "temp_c": 4.6,
        "feels_like_c": 4.6,
        "precip_prob": 10,
        "precip_mm": 0.0,
        "dewpoint_c": 3.6,
        "cloud_cover": 100,
        "wind_speed_kmh": 3.0,
        "condition": "Cloudy",
        "is_daytime": false
      },
      {
        "time": "2026-01-27T12:00:00Z",
        "temp_c": 4.0,
        "feels_like_c": 4.0,
        "precip_prob": 10,
        "precip_mm": 0.0,
        "dewpoint_c": 3.3,
        "cloud_cover": 100,
        "wind_speed_kmh": 5.0,
        "condition": "Cloudy",
        "is_daytime": false
      },
      {
        "time": "2026-01-27T13:00:00Z",
        "temp_c": 3.9,
        "feels_like_c": 3.0,
        "precip_prob": 10,
        "precip_mm": 0.0,
        "dewpoint_c": 3.2,
        "cloud_cover": 100,
        "wind_speed_kmh": 5.0,
        "condition": "Cloudy",
        "is_daytime": false
      },
      {
        "time": "2026-01-27T14:00:00Z",
        "temp_c": 3.6,
        "feels_like_c": 2.0,
        "precip_prob": 10,
        "precip_mm": 0.0,
        "dewpoint_c": 3.0,
        "cloud_cover": 100,
        "wind_speed_kmh": 5.0,
        "condition": "Cloudy",
        "is_daytime": false
      },
      {
        "time": "2026-01-27T15:00:00Z",
        "temp_c": 3.7,
        "feels_like_c": 2.0,
        "precip_prob": 10,
        "precip_mm": 0.0,
        "dewpoint_c": 3.3,
        "cloud_cover": 100,
        "wind_speed_kmh": 8.0,
        "condition": "Cloudy",
        "is_daytime": false
      },
      {
        "time": "2026-01-27T16:00:00Z",
        "temp_c": 4.2,
        "feels_like_c": 2.0,
        "precip_prob": 10,
        "precip_mm": 0.0,
        "dewpoint_c": 3.4,
        "cloud_cover": 100,
        "wind_speed_kmh": 10.0,
        "condition": "Cloudy",
        "is_daytime": true
      },
      {
        "time": "2026-01-27T17:00:00Z",
        "temp_c": 5.8,
        "feels_like_c": 4.0,
        "precip_prob": 10,
        "precip_mm": 0.0,
        "dewpoint_c": 4.4,
        "cloud_cover": 100,
        "wind_speed_kmh": 8.0,
        "condition": "Cloudy",
        "is_daytime": true
      },
      {
        "time": "2026-01-27T18:00:00Z",
        "temp_c": 7.6,
        "feels_like_c": 6.0,
        "precip_prob": 10,
        "precip_mm": 0.0,
        "dewpoint_c": 5.1,
        "cloud_cover": 96,
        "wind_speed_kmh": 10.0,
        "condition": "Cloudy",
        "is_daytime": true
      },
      {
        "time": "2026-01-27T19:00:00Z",
        "temp_c": 9.2,
        "feels_like_c": 8.0,
        "precip_prob": 10,
        "precip_mm": 0.0,
        "dewpoint_c": 5.5,
        "cloud_cover": 94,
        "wind_speed_kmh": 8.0,
        "condition": "Cloudy",
        "is_daytime": true
      },
      {
        "time": "2026-01-27T20:00:00Z",
        "temp_c": 10.7,
        "feels_like_c": 10.0,
        "precip_prob": 10,
        "precip_mm": 0.0,
        "dewpoint_c": 5.9,
        "cloud_cover": 83,
        "wind_speed_kmh": 8.0,
        "condition": "Mostly cloudy",
        "is_daytime": true
      },
      {
        "time": "2026-01-27T21:00:00Z",
        "temp_c": 12.1,
        "feels_like_c": 12.0,
        "precip_prob": 10,
        "precip_mm": 0.0,
        "dewpoint_c": 6.0,
        "cloud_cover": 85,
        "wind_speed_kmh": 8.0,
        "condition": "Mostly cloudy",
        "is_daytime": true
      },
      {
        "time": "2026-01-27T22:00:00Z",
        "temp_c": 13.1,
        "feels_like_c": 13.1,
        "precip_prob": 10,
        "precip_mm": 0.0,
        "dewpoint_c": 5.9,
        "cloud_cover": 76,
        "wind_speed_kmh": 3.0,
        "condition": "Mostly cloudy",
        "is_daytime": true
      },
      {
        "time": "2026-01-27T23:00:00Z",
        "temp_c": 14.1,
        "feels_like_c": 14.1,
        "precip_prob": 5,
        "precip_mm": 0.0,
        "dewpoint_c": 6.1,
        "cloud_cover": 60,
        "wind_speed_kmh": 3.0,
        "condition": "Partly sunny",
        "is_daytime": true
      },
      {
        "time": "2026-01-28T00:00:00Z",
        "temp_c": 14.1,
        "feels_like_c": 14.1,
        "precip_prob": 10,
        "precip_mm": 0.0,
        "dewpoint_c": 6.4,
        "cloud_cover": 67,
        "wind_speed_kmh": 2.0,
        "condition": "Mostly cloudy",
        "is_daytime": true
      },
      {
        "time": "2026-01-28T01:00:00Z",
        "temp_c": 13.3,
        "feels_like_c": 13.3,
        "precip_prob": 10,
        "precip_mm": 0.0,
        "dewpoint_c": 7.0,
        "cloud_cover": 90,
        "wind_speed_kmh": 2.0,
        "condition": "Cloudy",
        "is_daytime": true
      },
      {
        "time": "2026-01-28T02:00:00Z",
        "temp_c": 11.9,
        "feels_like_c": 11.9,
        "precip_prob": 10,
        "precip_mm": 0.0,
        "dewpoint_c": 6.9,
        "cloud_cover": 95,
        "wind_speed_kmh": 2.0,
        "condition": "Cloudy",
        "is_daytime": false
      },
      {
        "time": "2026-01-28T03:00:00Z",
        "temp_c": 11.1,
        "feels_like_c": 11.1,
        "precip_prob": 10,
        "precip_mm": 0.0,
        "dewpoint_c": 7.2,
        "cloud_cover": 100,
        "wind_speed_kmh": 2.0,
        "condition": "Cloudy",
        "is_daytime": false
      },
      {
        "time": "2026-01-28T04:00:00Z",
        "temp_c": 10.3,
        "feels_like_c": 10.3,
        "precip_prob": 10,
        "precip_mm": 0.0,
        "dewpoint_c": 7.1,
        "cloud_cover": 100,
        "wind_speed_kmh": 2.0,
        "condition": "Cloudy",
        "is_daytime": false
      },
      {
        "time": "2026-01-28T05:00:00Z",
        "temp_c": 10.2,
        "feels_like_c": 10.2,
        "precip_prob": 10,
        "precip_mm": 0.0,
        "dewpoint_c": 7.1,
        "cloud_cover": 100,
        "wind_speed_kmh": 3.0,
        "condition": "Cloudy",
        "is_daytime": false
      },
      {
        "time": "2026-01-28T06:00:00Z",
        "temp_c": 9.8,
        "feels_like_c": 9.8,
        "precip_prob": 10,
        "precip_mm": 0.0,
        "dewpoint_c": 6.7,
        "cloud_cover": 95,
        "wind_speed_kmh": 2.0,
        "condition": "Cloudy",
        "is_daytime": false
      },
      {
        "time": "2026-01-28T07:00:00Z",
        "temp_c": 8.9,
        "feels_like_c": 8.9,
        "precip_prob": 35,
        "precip_mm": 0.4394,
        "dewpoint_c": 6.3,
        "cloud_cover": 91,
        "wind_speed_kmh": 5.0,
        "condition": "Light rain",
        "is_daytime": false
      },
      {
        "time": "2026-01-28T08:00:00Z",
        "temp_c": 8.6,
        "feels_like_c": 7.0,
        "precip_prob": 75,
        "precip_mm": 2.0853,
        "dewpoint_c": 6.2,
        "cloud_cover": 69,
        "wind_speed_kmh": 8.0,
        "condition": "Rain",
        "is_daytime": false
      },
      {
        "time": "2026-01-28T09:00:00Z",
        "temp_c": 8.6,
        "feels_like_c": 7.0,
        "precip_prob": 35,
        "precip_mm": 0.2311,
        "dewpoint_c": 5.9,
        "cloud_cover": 76,
        "wind_speed_kmh": 10.0,
        "condition": "Light rain",
        "is_daytime": false
      },
      {
        "time": "2026-01-28T10:00:00Z",
        "temp_c": 8.4,
        "feels_like_c": 7.0,
        "precip_prob": 5,
        "precip_mm": 0.0,
        "dewpoint_c": 5.7,
        "cloud_cover": 56,
        "wind_speed_kmh": 10.0,
        "condition": "Partly cloudy",
        "is_daytime": false
      },
      {
        "time": "2026-01-28T11:00:00Z",
        "temp_c": 8.4,
        "feels_like_c": 8.0,
        "precip_prob": 5,
        "precip_mm": 0.0,
        "dewpoint_c": 5.9,
        "cloud_cover": 42,
        "wind_speed_kmh": 5.0,
        "condition": "Partly cloudy",
        "is_daytime": false
      },
      {
        "time": "2026-01-28T12:00:00Z",
        "temp_c": 7.7,
        "feels_like_c": 7.7,
        "precip_prob": 0,
        "precip_mm": 0.0,
        "dewpoint_c": 5.8,
        "cloud_cover": 32,
        "wind_speed_kmh": 2.0,
        "condition": "Partly cloudy",
        "is_daytime": false
      },
      {
        "time": "2026-01-28T13:00:00Z",
        "temp_c": 7.2,
        "feels_like_c": 7.2,
        "precip_prob": 0,
        "precip_mm": 0.0,
        "dewpoint_c": 5.6,
        "cloud_cover": 22,
        "wind_speed_kmh": 2.0,
        "condition": "Clear with periodic clouds",
        "is_daytime": false
      },
      {
        "time": "2026-01-28T14:00:00Z",
        "temp_c": 6.5,
        "feels_like_c": 6.5,
        "precip_prob": 0,
        "precip_mm": 0.0,
        "dewpoint_c": 5.4,
        "cloud_cover": 28,
        "wind_speed_kmh": 3.0,
        "condition": "Clear with periodic clouds",
        "is_daytime": false
      },
      {
        "time": "2026-01-28T15:00:00Z",
        "temp_c": 6.6,
        "feels_like_c": 5.0,
        "precip_prob": 0,
        "precip_mm": 0.0,
        "dewpoint_c": 5.3,
        "cloud_cover": 30,
        "wind_speed_kmh": 6.0,
        "condition": "Partly cloudy",
        "is_daytime": false
      },
      {
        "time": "2026-01-28T16:00:00Z",
        "temp_c": 7.6,
        "feels_like_c": 6.0,
        "precip_prob": 5,
        "precip_mm": 0.0,
        "dewpoint_c": 5.9,
        "cloud_cover": 50,
        "wind_speed_kmh": 10.0,
        "condition": "Partly sunny",
        "is_daytime": true
      },
      {
        "time": "2026-01-28T17:00:00Z",
        "temp_c": 9.7,
        "feels_like_c": 8.0,
        "precip_prob": 5,
        "precip_mm": 0.0,
        "dewpoint_c": 7.2,
        "cloud_cover": 54,
        "wind_speed_kmh": 11.0,
        "condition": "Partly sunny",
        "is_daytime": true
      },
      {
        "time": "2026-01-28T18:00:00Z",
        "temp_c": 12.1,
        "feels_like_c": 11.0,
        "precip_prob": 5,
        "precip_mm": 0.0,
        "dewpoint_c": 7.9,
        "cloud_cover": 56,
        "wind_speed_kmh": 10.0,
        "condition": "Partly sunny",
        "is_daytime": true
      },
      {
        "time": "2026-01-28T19:00:00Z",
        "temp_c": 14.1,
        "feels_like_c": 13.0,
        "precip_prob": 5,
        "precip_mm": 0.0,
        "dewpoint_c": 8.3,
        "cloud_cover": 52,
        "wind_speed_kmh": 11.0,
        "condition": "Partly sunny",
        "is_daytime": true
      },
      {
        "time": "2026-01-28T20:00:00Z",
        "temp_c": 15.2,
        "feels_like_c": 15.0,
        "precip_prob": 10,
        "precip_mm": 0.0,
        "dewpoint_c": 8.5,
        "cloud_cover": 80,
        "wind_speed_kmh": 11.0,
        "condition": "Mostly cloudy",
        "is_daytime": true
      },
      {
        "time": "2026-01-28T21:00:00Z",
        "temp_c": 15.6,
        "feels_like_c": 15.0,
        "precip_prob": 10,
        "precip_mm": 0.0,
        "dewpoint_c": 8.7,
        "cloud_cover": 76,
        "wind_speed_kmh": 13.0,
        "condition": "Mostly cloudy",
        "is_daytime": true
      },
      {
        "time": "2026-01-28T22:00:00Z",
        "temp_c": 15.5,
        "feels_like_c": 15.0,
        "precip_prob": 5,
        "precip_mm": 0.0,
        "dewpoint_c": 8.7,
        "cloud_cover": 45,
        "wind_speed_kmh": 14.0,
        "condition": "Partly sunny",
        "is_daytime": true
      },
      {
        "time": "2026-01-28T23:00:00Z",
        "temp_c": 15.6,
        "feels_like_c": 15.0,
        "precip_prob": 0,
        "precip_mm": 0.0,
        "dewpoint_c": 8.3,
        "cloud_cover": 40,
        "wind_speed_kmh": 18.0,
        "condition": "Partly sunny",
        "is_daytime": true
      },
      {
        "time": "2026-01-29T00:00:00Z",
        "temp_c": 15.2,
        "feels_like_c": 14.0,
        "precip_prob": 0,
        "precip_mm": 0.0,
        "dewpoint_c": 7.8,
        "cloud_cover": 40,
        "wind_speed_kmh": 16.0,
        "condition": "Partly sunny",
        "is_daytime": true
      },
      {
        "time": "2026-01-29T01:00:00Z",
        "temp_c": 14.2,
        "feels_like_c": 13.0,
        "precip_prob": 0,
        "precip_mm": 0.0,
        "dewpoint_c": 8.3,
        "cloud_cover": 35,
        "wind_speed_kmh": 14.0,
        "condition": "Partly sunny",
        "is_daytime": true
      },
      {
        "time": "2026-01-29T02:00:00Z",
        "temp_c": 13.1,
        "feels_like_c": 12.0,
        "precip_prob": 0,
        "precip_mm": 0.0,
        "dewpoint_c": 8.1,
        "cloud_cover": 32,
        "wind_speed_kmh": 14.0,
        "condition": "Partly cloudy",
        "is_daytime": false
      },
      {
        "time": "2026-01-29T03:00:00Z",
        "temp_c": 12.3,
        "feels_like_c": 11.0,
        "precip_prob": 0,
        "precip_mm": 0.0,
        "dewpoint_c": 8.1,
        "cloud_cover": 30,
        "wind_speed_kmh": 11.0,
        "condition": "Partly cloudy",
        "is_daytime": false
      },
      {
        "time": "2026-01-29T04:00:00Z",
        "temp_c": 11.3,
        "feels_like_c": 10.0,
        "precip_prob": 0,
        "precip_mm": 0.0,
        "dewpoint_c": 7.6,
        "cloud_cover": 25,
        "wind_speed_kmh": 11.0,
        "condition": "Clear with periodic clouds",
        "is_daytime": false
      },
      {
        "time": "2026-01-29T05:00:00Z",
        "temp_c": 10.6,
        "feels_like_c": 9.0,
        "precip_prob": 0,
        "precip_mm": 0.0,
        "dewpoint_c": 7.3,
        "cloud_cover": 25,
        "wind_speed_kmh": 11.0,
        "condition": "Clear with periodic clouds",
        "is_daytime": false
      },
      {
        "time": "2026-01-29T06:00:00Z",
        "temp_c": 9.9,
        "feels_like_c": 8.0,
        "precip_prob": 0,
        "precip_mm": 0.0,
        "dewpoint_c": 6.7,
        "cloud_cover": 25,
        "wind_speed_kmh": 11.0,
        "condition": "Clear with periodic clouds",
        "is_daytime": false
      },
      {
        "time": "2026-01-29T07:00:00Z",
        "temp_c": 9.2,
        "feels_like_c": 8.0,
        "precip_prob": 0,
        "precip_mm": 0.0,
        "dewpoint_c": 6.3,
        "cloud_cover": 30,
        "wind_speed_kmh": 10.0,
        "condition": "Partly cloudy",
        "is_daytime": false
      },
      {
        "time": "2026-01-29T08:00:00Z",
        "temp_c": 8.6,
        "feels_like_c": 7.0,
        "precip_prob": 0,
        "precip_mm": 0.0,
        "dewpoint_c": 6.2,
        "cloud_cover": 34,
        "wind_speed_kmh": 10.0,
        "condition": "Partly cloudy",
        "is_daytime": false
      },
      {
        "time": "2026-01-29T09:00:00Z",
        "temp_c": 8.2,
        "feels_like_c": 7.0,
        "precip_prob": 0,
        "precip_mm": 0.0,
        "dewpoint_c": 6.1,
        "cloud_cover": 37,
        "wind_speed_kmh": 8.0,
        "condition": "Partly cloudy",
        "is_daytime": false
      },
      {
        "time": "2026-01-29T10:00:00Z",
        "temp_c": 7.8,
        "feels_like_c": 6.0,
        "precip_prob": 5,
        "precip_mm": 0.0,
        "dewpoint_c": 5.8,
        "cloud_cover": 54,
        "wind_speed_kmh": 8.0,
        "condition": "Partly cloudy",
        "is_daytime": false
      },
      {
        "time": "2026-01-29T11:00:00Z",
        "temp_c": 7.6,
        "feels_like_c": 6.0,
        "precip_prob": 10,
        "precip_mm": 0.0,
        "dewpoint_c": 5.8,
        "cloud_cover": 70,
        "wind_speed_kmh": 6.0,
        "condition": "Mostly cloudy",
        "is_daytime": false
      },
      {
        "time": "2026-01-29T12:00:00Z",
        "temp_c": 7.1,
        "feels_like_c": 6.0,
        "precip_prob": 10,
        "precip_mm": 0.0,
        "dewpoint_c": 5.7,
        "cloud_cover": 85,
        "wind_speed_kmh": 6.0,
        "condition": "Mostly cloudy",
        "is_daytime": false
      },
      {
        "time": "2026-01-29T13:00:00Z",
        "temp_c": 6.8,
        "feels_like_c": 6.0,
        "precip_prob": 10,
        "precip_mm": 0.0,
        "dewpoint_c": 5.6,
        "cloud_cover": 85,
        "wind_speed_kmh": 5.0,
        "condition": "Mostly cloudy",
        "is_daytime": false
      },
      {
        "time": "2026-01-29T14:00:00Z",
        "temp_c": 6.5,
        "feels_like_c": 6.5,
        "precip_prob": 10,
        "precip_mm": 0.0,
        "dewpoint_c": 5.4,
        "cloud_cover": 87,
        "wind_speed_kmh": 2.0,
        "condition": "Mostly cloudy",
        "is_daytime": false
      },
      {
        "time": "2026-01-29T15:00:00Z",
        "temp_c": 6.4,
        "feels_like_c": 6.4,
        "precip_prob": 10,
        "precip_mm": 0.0,
        "dewpoint_c": 5.4,
        "cloud_cover": 89,
        "wind_speed_kmh": 0.0,
        "condition": "Mostly cloudy",
        "is_daytime": false
      },
      {
        "time": "2026-01-29T16:00:00Z",
        "temp_c": 6.7,
        "feels_like_c": 6.7,
        "precip_prob": 10,
        "precip_mm": 0.0,
        "dewpoint_c": 5.8,
        "cloud_cover": 84,
        "wind_speed_kmh": 2.0,
        "condition": "Mostly cloudy",
        "is_daytime": true
      },
      {
        "time": "2026-01-29T17:00:00Z",
        "temp_c": 8.1,
        "feels_like_c": 8.1,
        "precip_prob": 10,
        "precip_mm": 0.0,
        "dewpoint_c": 6.8,
        "cloud_cover": 80,
        "wind_speed_kmh": 3.0,
        "condition": "Mostly cloudy",
        "is_daytime": true
      },
      {
        "time": "2026-01-29T18:00:00Z",
        "temp_c": 9.5,
        "feels_like_c": 9.0,
        "precip_prob": 10,
        "precip_mm": 0.0,
        "dewpoint_c": 7.4,
        "cloud_cover": 79,
        "wind_speed_kmh": 5.0,
        "condition": "Mostly cloudy",
        "is_daytime": true
      },
      {
        "time": "2026-01-29T19:00:00Z",
        "temp_c": 10.6,
        "feels_like_c": 10.6,
        "precip_prob": 5,
        "precip_mm": 0.0,
        "dewpoint_c": 7.4,
        "cloud_cover": 64,
        "wind_speed_kmh": 3.0,
        "condition": "Partly sunny",
        "is_daytime": true
      },
      {
        "time": "2026-01-29T20:00:00Z",
        "temp_c": 11.4,
        "feels_like_c": 11.4,
        "precip_prob": 5,
        "precip_mm": 0.0,
        "dewpoint_c": 7.7,
        "cloud_cover": 46,
        "wind_speed_kmh": 3.0,
        "condition": "Partly sunny",
        "is_daytime": true
      },
      {
        "time": "2026-01-29T21:00:00Z",
        "temp_c": 12.5,
        "feels_like_c": 12.5,
        "precip_prob": 0,
        "precip_mm": 0.0,
        "dewpoint_c": 7.8,
        "cloud_cover": 31,
        "wind_speed_kmh": 2.0,
        "condition": "Partly sunny",
        "is_daytime": true
      },
      {
        "time": "2026-01-29T22:00:00Z",
        "temp_c": 13.2,
        "feels_like_c": 13.2,
        "precip_prob": 5,
        "precip_mm": 0.0,
        "dewpoint_c": 7.8,
        "cloud_cover": 41,
        "wind_speed_kmh": 2.0,
        "condition": "Partly sunny",
        "is_daytime": true
      },
      {
        "time": "2026-01-29T23:00:00Z",
        "temp_c": 14.4,
        "feels_like_c": 14.4,
        "precip_prob": 5,
        "precip_mm": 0.0,
        "dewpoint_c": 7.9,
        "cloud_cover": 50,
        "wind_speed_kmh": 3.0,
        "condition": "Partly sunny",
        "is_daytime": true
      },
      {
        "time": "2026-01-30T00:00:00Z",
        "temp_c": 14.7,
        "feels_like_c": 14.7,
        "precip_prob": 5,
        "precip_mm": 0.0,
        "dewpoint_c": 8.1,
        "cloud_cover": 60,
        "wind_speed_kmh": 3.0,
        "condition": "Partly sunny",
        "is_daytime": true
      },
      {
        "time": "2026-01-30T01:00:00Z",
        "temp_c": 14.0,
        "feels_like_c": 14.0,
        "precip_prob": 5,
        "precip_mm": 0.0,
        "dewpoint_c": 8.2,
        "cloud_cover": 60,
        "wind_speed_kmh": 3.0,
        "condition": "Partly sunny",
        "is_daytime": true
      },
      {
        "time": "2026-01-30T02:00:00Z",
        "temp_c": 12.6,
        "feels_like_c": 12.6,
        "precip_prob": 5,
        "precip_mm": 0.0,
        "dewpoint_c": 8.0,
        "cloud_cover": 55,
        "wind_speed_kmh": 3.0,
        "condition": "Partly cloudy",
        "is_daytime": false
      },
      {
        "time": "2026-01-30T03:00:00Z",
        "temp_c": 11.1,
        "feels_like_c": 11.1,
        "precip_prob": 5,
        "precip_mm": 0.0,
        "dewpoint_c": 8.1,
        "cloud_cover": 51,
        "wind_speed_kmh": 3.0,
        "condition": "Partly cloudy",
        "is_daytime": false
      },
      {
        "time": "2026-01-30T04:00:00Z",
        "temp_c": 9.8,
        "feels_like_c": 9.0,
        "precip_prob": 5,
        "precip_mm": 0.0,
        "dewpoint_c": 7.6,
        "cloud_cover": 61,
        "wind_speed_kmh": 5.0,
        "condition": "Partly cloudy",
        "is_daytime": false
      },
      {
        "time": "2026-01-30T05:00:00Z",
        "temp_c": 9.1,
        "feels_like_c": 9.0,
        "precip_prob": 10,
        "precip_mm": 0.0,
        "dewpoint_c": 7.2,
        "cloud_cover": 70,
        "wind_speed_kmh": 5.0,
        "condition": "Mostly cloudy",
        "is_daytime": false
      },
      {
        "time": "2026-01-30T06:00:00Z",
        "temp_c": 8.6,
        "feels_like_c": 8.0,
        "precip_prob": 10,
        "precip_mm": 0.0,
        "dewpoint_c": 6.7,
        "cloud_cover": 80,
        "wind_speed_kmh": 8.0,
        "condition": "Mostly cloudy",
        "is_daytime": false
      },
      {
        "time": "2026-01-30T07:00:00Z",
        "temp_c": 8.2,
        "feels_like_c": 7.0,
        "precip_prob": 10,
        "precip_mm": 0.0,
        "dewpoint_c": 6.5,
        "cloud_cover": 75,
        "wind_speed_kmh": 8.0,
        "condition": "Mostly cloudy",
        "is_daytime": false
      },
      {
        "time": "2026-01-30T08:00:00Z",
        "temp_c": 7.8,
        "feels_like_c": 7.0,
        "precip_prob": 10,
        "precip_mm": 0.0,
        "dewpoint_c": 6.2,
        "cloud_cover": 75,
        "wind_speed_kmh": 8.0,
        "condition": "Mostly cloudy",
        "is_daytime": false
      },
      {
        "time": "2026-01-30T09:00:00Z",
        "temp_c": 7.6,
        "feels_like_c": 6.0,
        "precip_prob": 10,
        "precip_mm": 0.0,
        "dewpoint_c": 6.0,
        "cloud_cover": 75,
        "wind_speed_kmh": 8.0,
        "condition": "Mostly cloudy",
        "is_daytime": false
      },
      {
        "time": "2026-01-30T10:00:00Z",
        "temp_c": 7.4,
        "feels_like_c": 6.0,
        "precip_prob": 10,
        "precip_mm": 0.0,
        "dewpoint_c": 6.0,
        "cloud_cover": 80,
        "wind_speed_kmh": 8.0,
        "condition": "Mostly cloudy",
        "is_daytime": false
      },
      {
        "time": "2026-01-30T11:00:00Z",
        "temp_c": 7.2,
        "feels_like_c": 6.0,
        "precip_prob": 10,
        "precip_mm": 0.0,
        "dewpoint_c": 6.1,
        "cloud_cover": 85,
        "wind_speed_kmh": 8.0,
        "condition": "Mostly cloudy",
        "is_daytime": false
      },
      {
        "time": "2026-01-30T12:00:00Z",
        "temp_c": 7.1,
        "feels_like_c": 6.0,
        "precip_prob": 10,
        "precip_mm": 0.0,
        "dewpoint_c": 6.1,
        "cloud_cover": 94,
        "wind_speed_kmh": 8.0,
        "condition": "Cloudy",
        "is_daytime": false
      }
    ],
    "daily": [
      {
        "date": "2026-01-25",
        "high_c": 6.3,
        "low_c": 5.1,
        "high_f": 43,
        "low_f": 41,
        "precip_prob": 10,
        "condition": "Unknown"
      },
      {
        "date": "2026-01-26",
        "high_c": 12.6,
        "low_c": 3.9,
        "high_f": 55,
        "low_f": 39,
        "precip_prob": 10,
        "condition": "Partly sunny"
      },
      {
        "date": "2026-01-27",
        "high_c": 14.1,
        "low_c": 3.6,
        "high_f": 57,
        "low_f": 38,
        "precip_prob": 75,
        "condition": "Cloudy"
      },
      {
        "date": "2026-01-28",
        "high_c": 15.6,
        "low_c": 6.5,
        "high_f": 60,
        "low_f": 44,
        "precip_prob": 10,
        "condition": "Partly sunny"
      },
      {
        "date": "2026-01-29",
        "high_c": 14.7,
        "low_c": 6.4,
        "high_f": 58,
        "low_f": 44,
        "precip_prob": 10,
        "condition": "Partly sunny"
      }
    ],
    "source": "Google Weather API (MetNet-3)",
    "fetched_at": "2026-01-26T05:35:49.335956"
  }
}